README.md
setup.py
src/librustypy/Cargo.toml
src/librustypy/__init__.py
src/librustypy/lib.rs
src/librustypy/macros.rs
src/librustypy/pytypes/mod.rs
src/librustypy/pytypes/pybool.rs
src/librustypy/pytypes/pydict.rs
src/librustypy/pytypes/pylist.rs
src/librustypy/pytypes/pystring.rs
src/librustypy/pytypes/pytuple.rs
src/rustypy/__init__.py
src/rustypy/__main__.py
src/rustypy/pywrapper.py
src/rustypy/scripts.py
src/rustypy/type_checkers.py
src/rustypy.egg-info/PKG-INFO
src/rustypy.egg-info/SOURCES.txt
src/rustypy.egg-info/dependency_links.txt
src/rustypy.egg-info/entry_points.txt
src/rustypy.egg-info/top_level.txt
src/rustypy/rswrapper/__init__.py
src/rustypy/rswrapper/ffi_defs.py
src/rustypy/rswrapper/pytypes.py
src/rustypy/rswrapper/rswrapper.py