Metadata-Version: 1.1
Name: rustypy
Version: 0.1.16
Summary: Automatic FFI generation for Python <-> Rust interfacing.
Home-page: https://github.com/iduartgomez/rustypy
Author: Ignacio Duart Gómez
Author-email: iduartgomez@gmail.com
License: BSD 3-Clause
Keywords: rust autogenerated FFI
Platform: UNKNOWN
Classifier: Intended Audience :: Developers
Classifier: License :: OSI Approved :: MIT License
Classifier: Operating System :: POSIX
Classifier: Programming Language :: Python :: 3.5
Classifier: Programming Language :: Python :: 3.6
Classifier: Programming Language :: Python :: 3.7
Classifier: Programming Language :: Python :: 3.8
Classifier: Programming Language :: Rust
Classifier: Topic :: Software Development :: Code Generators
